README.md
setup.py
xtempmail/__init__.py
xtempmail/aiomail.py
xtempmail/error.py
xtempmail/logger.py
xtempmail/mail.py
xtempmail/utils.py
xtempmail.egg-info/PKG-INFO
xtempmail.egg-info/SOURCES.txt
xtempmail.egg-info/dependency_links.txt
xtempmail.egg-info/requires.txt
xtempmail.egg-info/top_level.txt