Metadata-Version: 2.1
Name: xtempmail
Version: 0.9
Summary: Temporary Email
Home-page: https://github.com/krypton-byte/xtempmail
Author: Krypton Byte
Author-email: galaxyvplus6434@gmail.com
License: MIT
Keywords: temporary,mail,email,autoreply
Classifier: Development Status :: 3 - Alpha
Classifier: Intended Audience :: Developers
Classifier: Topic :: Software Development :: Build Tools
Classifier: License :: OSI Approved :: MIT License
Classifier: Programming Language :: Python :: 3.8
Classifier: Programming Language :: Python :: 3.9
